{"layouts": [{"canvaswidth": 2560, "canvasheight": 1440, "elements": [{"width": 279, "height": 1440, "x": 84, "y": 0}, {"width": 227, "height": 605, "x": 134, "y": 252}, {"width": 279, "height": 196, "x": 84, "y": 0}, {"width": 265, "height": 1440, "x": 97, "y": 1272}, {"width": 448, "height": 1440, "x": 279, "y": 0}, {"width": 448, "height": 1440, "x": 279, "y": 0}, {"width": 2392, "height": 360, "x": 2196, "y": 0}, {"width": 2392, "height": 720, "x": 2196, "y": 360}, {"width": 2392, "height": 1080, "x": 2196, "y": 720}, {"width": 2392, "height": 1440, "x": 2196, "y": 1080}, {"width": 1301, "height": 713, "x": 462, "y": 14}, {"width": 986, "height": 713, "x": 910, "y": 14}, {"width": 1052, "height": 713, "x": 995, "y": 14}, {"width": 1301, "height": 289, "x": 1132, "y": 14}, {"width": 1301, "height": 1426, "x": 462, "y": 727}, {"width": 986, "height": 1426, "x": 910, "y": 727}, {"width": 1052, "height": 1426, "x": 995, "y": 727}, {"width": 1301, "height": 1002, "x": 1132, "y": 727}, {"width": 2154, "height": 713, "x": 1315, "y": 14}, {"width": 1839, "height": 713, "x": 1763, "y": 14}, {"width": 1905, "height": 713, "x": 1848, "y": 14}, {"width": 2154, "height": 289, "x": 1985, "y": 14}, {"width": 2154, "height": 1426, "x": 1315, "y": 727}, {"width": 1839, "height": 1426, "x": 1763, "y": 727}, {"width": 1905, "height": 1426, "x": 1848, "y": 727}, {"width": 2154, "height": 1002, "x": 1985, "y": 727}, {"width": 2392, "height": 713, "x": 2168, "y": 14}, {"width": 2392, "height": 1426, "x": 2168, "y": 727}]}]}