{"layouts": [{"canvaswidth": 2560, "canvasheight": 1440, "elements": [{"width": 280, "height": 1440, "x": 84, "y": 0}, {"width": 220, "height": 1272, "x": 144, "y": 196}, {"width": 280, "height": 196, "x": 84, "y": 0}, {"width": 266, "height": 1440, "x": 98, "y": 1272}, {"width": 1045, "height": 1387, "x": 815, "y": 53}, {"width": 1653, "height": 1268, "x": 1577, "y": 172}, {"width": 1856, "height": 623, "x": 1688, "y": 53}, {"width": 1168, "height": 1387, "x": 1063, "y": 53}, {"width": 1291, "height": 1387, "x": 1186, "y": 53}, {"width": 1449, "height": 1387, "x": 1309, "y": 53}, {"width": 1559, "height": 394, "x": 1502, "y": 53}, {"width": 1559, "height": 1387, "x": 1502, "y": 1041}]}]}