{"layouts": [{"canvaswidth": 2560, "canvasheight": 1440, "elements": [{"width": 280, "height": 1440, "x": 84, "y": 0}, {"width": 227, "height": 308, "x": 136, "y": 56}, {"width": 266, "height": 1440, "x": 98, "y": 1272}, {"width": 2392, "height": 360, "x": 2196, "y": 0}, {"width": 2392, "height": 720, "x": 2196, "y": 360}, {"width": 2392, "height": 1080, "x": 2196, "y": 720}, {"width": 2392, "height": 1440, "x": 2196, "y": 1080}, {"width": 444, "height": 1440, "x": 280, "y": 0}, {"width": 374, "height": 1384, "x": 298, "y": 252}, {"width": 903, "height": 1440, "x": 444, "y": 0}, {"width": 676, "height": 856, "x": 590, "y": 252}, {"width": 654, "height": 196, "x": 514, "y": 56}, {"width": 590, "height": 1262, "x": 514, "y": 252}, {"width": 584, "height": 1331, "x": 519, "y": 1262}, {"width": 568, "height": 1384, "x": 536, "y": 1352}, {"width": 833, "height": 1384, "x": 757, "y": 252}, {"width": 1362, "height": 1440, "x": 903, "y": 0}, {"width": 1135, "height": 1199, "x": 1049, "y": 252}, {"width": 1113, "height": 196, "x": 973, "y": 56}, {"width": 1049, "height": 1262, "x": 973, "y": 252}, {"width": 1043, "height": 1331, "x": 978, "y": 1262}, {"width": 1027, "height": 1384, "x": 995, "y": 1352}, {"width": 1292, "height": 1384, "x": 1216, "y": 252}, {"width": 1664, "height": 1440, "x": 1362, "y": 0}, {"width": 1594, "height": 377, "x": 1508, "y": 252}, {"width": 1572, "height": 196, "x": 1432, "y": 56}, {"width": 1508, "height": 1262, "x": 1432, "y": 252}, {"width": 1502, "height": 1331, "x": 1437, "y": 1262}, {"width": 1486, "height": 1384, "x": 1454, "y": 1352}, {"width": 2123, "height": 1440, "x": 1664, "y": 0}, {"width": 1896, "height": 632, "x": 1810, "y": 252}, {"width": 1874, "height": 196, "x": 1734, "y": 56}, {"width": 1810, "height": 1262, "x": 1734, "y": 252}, {"width": 1804, "height": 1331, "x": 1739, "y": 1262}, {"width": 1788, "height": 1384, "x": 1756, "y": 1352}, {"width": 2053, "height": 1384, "x": 1977, "y": 252}]}]}