{"layouts": [{"canvaswidth": 2392, "canvasheight": 1440, "elements": [{"width": 252, "height": 1440, "x": 84, "y": 0}, {"width": 252, "height": 852, "x": 84, "y": 656}, {"width": 252, "height": 1048, "x": 84, "y": 852}, {"width": 252, "height": 1244, "x": 84, "y": 1048}, {"width": 252, "height": 1440, "x": 84, "y": 1244}, {"width": 224, "height": 155, "x": 112, "y": 43}, {"width": 210, "height": 314, "x": 125, "y": 169}, {"width": 2392, "height": 1440, "x": 252, "y": 0}, {"width": 410, "height": 300, "x": 302, "y": 159}, {"width": 618, "height": 558, "x": 502, "y": 214}, {"width": 816, "height": 573, "x": 702, "y": 109}, {"width": 1016, "height": 525, "x": 902, "y": 153}, {"width": 1201, "height": 679, "x": 1102, "y": 105}, {"width": 1423, "height": 834, "x": 1302, "y": 208}, {"width": 1612, "height": 615, "x": 1502, "y": 157}, {"width": 1823, "height": 1099, "x": 1702, "y": 121}, {"width": 2015, "height": 505, "x": 1902, "y": 131}, {"width": 2225, "height": 585, "x": 2102, "y": 112}]}]}