{"layouts": [{"canvaswidth": 2560, "canvasheight": 1440, "elements": [{"width": 2392, "height": 1440, "x": 0, "y": 0}, {"width": 1778, "height": 25, "x": 1729, "y": 0}, {"width": 252, "height": 1440, "x": 84, "y": 0}, {"width": 252, "height": 1440, "x": 84, "y": 1234}, {"width": 252, "height": 161, "x": 84, "y": 0}, {"width": 224, "height": 1220, "x": 112, "y": 1108}, {"width": 2350, "height": 1398, "x": 2196, "y": 1244}, {"width": 2324, "height": 1356, "x": 2222, "y": 1286}, {"width": 2350, "height": 1398, "x": 2196, "y": 1244}, {"width": 2392, "height": 1440, "x": 0, "y": 0}, {"width": 2392, "height": 1440, "x": 0, "y": 0}, {"width": 1575, "height": 1440, "x": 0, "y": 0}, {"width": 2156, "height": 1440, "x": 1575, "y": 0}, {"width": 1694, "height": 1363, "x": 1623, "y": 0}, {"width": 1680, "height": 1405, "x": 1638, "y": 1363}, {"width": 2100, "height": 322, "x": 1743, "y": 0}, {"width": 2030, "height": 308, "x": 1743, "y": 14}, {"width": 2100, "height": 308, "x": 2030, "y": 14}, {"width": 2279, "height": 1440, "x": 2156, "y": 0}, {"width": 2279, "height": 480, "x": 2156, "y": 0}, {"width": 2279, "height": 960, "x": 2156, "y": 480}, {"width": 2279, "height": 1440, "x": 2156, "y": 960}, {"width": 2392, "height": 1440, "x": 2279, "y": 0}, {"width": 2392, "height": 1405, "x": 2360, "y": 35}, {"width": 2346, "height": 305, "x": 2293, "y": 35}, {"width": 682, "height": 909, "x": 304, "y": 531}, {"width": 1575, "height": 1440, "x": 0, "y": 0}, {"width": 1575, "height": 1440, "x": 0, "y": 0}, {"width": 834, "height": 1009, "x": 741, "y": 431}, {"width": 1007, "height": 933, "x": 960, "y": 506}, {"width": 1126, "height": 856, "x": 1028, "y": 583}, {"width": 1573, "height": 480, "x": 1379, "y": 0}, {"width": 1573, "height": 960, "x": 1379, "y": 480}, {"width": 1573, "height": 1440, "x": 1379, "y": 960}, {"width": 946, "height": 609, "x": 848, "y": 511}, {"width": 921, "height": 928, "x": 874, "y": 609}]}]}