{"layouts": [{"canvaswidth": 2560, "canvasheight": 1440, "elements": [{"width": 280, "height": 1440, "x": 84, "y": 0}, {"width": 224, "height": 1440, "x": 139, "y": 196}, {"width": 280, "height": 196, "x": 84, "y": 0}, {"width": 2392, "height": 1440, "x": 280, "y": 0}, {"width": 2025, "height": 242, "x": 1922, "y": 56}, {"width": 2273, "height": 188, "x": 1973, "y": 56}, {"width": 2273, "height": 1412, "x": 2135, "y": 1195}, {"width": 2392, "height": 1440, "x": 280, "y": 0}, {"width": 1461, "height": 1385, "x": 1258, "y": 1182}, {"width": 1678, "height": 1385, "x": 1475, "y": 1182}, {"width": 1895, "height": 1385, "x": 1692, "y": 1182}, {"width": 2168, "height": 1412, "x": 1909, "y": 1154}]}]}