{"layouts": [{"canvaswidth": 2392, "canvasheight": 1440, "elements": [{"width": 2392, "height": 1280, "x": 2217, "y": 160}, {"width": 149, "height": 147, "x": 9, "y": 7}, {"width": 158, "height": 1212, "x": 0, "y": 158}, {"width": 149, "height": 1433, "x": 9, "y": 1223}, {"width": 560, "height": 527, "x": 210, "y": 177}, {"width": 560, "height": 895, "x": 210, "y": 545}, {"width": 560, "height": 1263, "x": 210, "y": 913}, {"width": 945, "height": 527, "x": 595, "y": 177}, {"width": 945, "height": 895, "x": 595, "y": 545}, {"width": 945, "height": 1263, "x": 595, "y": 913}, {"width": 1330, "height": 527, "x": 980, "y": 177}, {"width": 1330, "height": 895, "x": 980, "y": 545}, {"width": 1330, "height": 1263, "x": 980, "y": 913}]}]}