{"layouts": [{"canvaswidth": 2560, "canvasheight": 1440, "elements": [{"width": 280, "height": 1440, "x": 84, "y": 0}, {"width": 228, "height": 511, "x": 135, "y": 252}, {"width": 280, "height": 196, "x": 84, "y": 0}, {"width": 494, "height": 1440, "x": 280, "y": 0}, {"width": 427, "height": 587, "x": 342, "y": 53}, {"width": 427, "height": 1387, "x": 342, "y": 587}, {"width": 764, "height": 1440, "x": 494, "y": 0}, {"width": 974, "height": 1440, "x": 764, "y": 0}, {"width": 1244, "height": 1440, "x": 974, "y": 0}]}]}