{"layouts": [{"canvaswidth": 2560, "canvasheight": 1440, "elements": [{"width": 2392, "height": 980, "x": 0, "y": 0}, {"width": 747, "height": 980, "x": 579, "y": 0}, {"width": 915, "height": 980, "x": 747, "y": 0}, {"width": 1143, "height": 980, "x": 975, "y": 0}, {"width": 1311, "height": 980, "x": 1143, "y": 0}, {"width": 1479, "height": 980, "x": 1311, "y": 0}, {"width": 551, "height": 980, "x": 0, "y": 0}, {"width": 411, "height": 252, "x": 215, "y": 56}, {"width": 500, "height": 396, "x": 434, "y": 56}, {"width": 280, "height": 1440, "x": 84, "y": 0}, {"width": 228, "height": 507, "x": 135, "y": 252}, {"width": 280, "height": 196, "x": 84, "y": 0}, {"width": 266, "height": 1440, "x": 98, "y": 1272}, {"width": 1490, "height": 801, "x": 1397, "y": 638}, {"width": 1598, "height": 889, "x": 1532, "y": 551}, {"width": 1878, "height": 874, "x": 1710, "y": 566}, {"width": 1341, "height": 1008, "x": 765, "y": 432}]}]}