{"layouts": [{"canvaswidth": 2392, "canvasheight": 1440, "elements": [{"width": 168, "height": 1440, "x": 0, "y": 0}, {"width": 140, "height": 155, "x": 28, "y": 43}, {"width": 135, "height": 568, "x": 32, "y": 169}, {"width": 2392, "height": 1440, "x": 2217, "y": 0}, {"width": 2392, "height": 1440, "x": 2217, "y": 0}, {"width": 2392, "height": 1440, "x": 2217, "y": 0}, {"width": 425, "height": 1440, "x": 168, "y": 0}, {"width": 396, "height": 895, "x": 168, "y": 545}, {"width": 835, "height": 1440, "x": 427, "y": 0}, {"width": 806, "height": 895, "x": 456, "y": 545}, {"width": 1245, "height": 1440, "x": 837, "y": 0}, {"width": 1216, "height": 895, "x": 866, "y": 545}, {"width": 1655, "height": 1440, "x": 1247, "y": 0}, {"width": 1626, "height": 895, "x": 1276, "y": 545}, {"width": 2065, "height": 1440, "x": 1657, "y": 0}, {"width": 2036, "height": 895, "x": 1686, "y": 545}, {"width": 2217, "height": 1440, "x": 2067, "y": 0}, {"width": 2217, "height": 895, "x": 2096, "y": 545}]}]}