{"layouts": [{"canvaswidth": 2560, "canvasheight": 1440, "elements": [{"width": 280, "height": 1440, "x": 84, "y": 0}, {"width": 280, "height": 196, "x": 84, "y": 0}, {"width": 228, "height": 556, "x": 135, "y": 252}, {"width": 259, "height": 1132, "x": 104, "y": 868}, {"width": 266, "height": 1300, "x": 98, "y": 1132}, {"width": 266, "height": 1440, "x": 98, "y": 1300}, {"width": 455, "height": 1280, "x": 280, "y": 160}, {"width": 455, "height": 1280, "x": 280, "y": 160}, {"width": 455, "height": 1280, "x": 280, "y": 160}, {"width": 708, "height": 1440, "x": 483, "y": 0}, {"width": 708, "height": 1440, "x": 483, "y": 1198}, {"width": 614, "height": 1170, "x": 511, "y": 39}, {"width": 680, "height": 172, "x": 614, "y": 39}, {"width": 940, "height": 1440, "x": 715, "y": 0}, {"width": 940, "height": 1440, "x": 715, "y": 1198}, {"width": 846, "height": 1170, "x": 743, "y": 39}, {"width": 912, "height": 172, "x": 846, "y": 39}, {"width": 1172, "height": 1440, "x": 947, "y": 0}, {"width": 1172, "height": 1440, "x": 947, "y": 1198}, {"width": 1078, "height": 1170, "x": 975, "y": 39}, {"width": 1144, "height": 119, "x": 1078, "y": 39}]}]}