{"layouts": [{"canvaswidth": 2560, "canvasheight": 1440, "elements": [{"width": 218, "height": 280, "x": 84, "y": 146}, {"width": 218, "height": 983, "x": 84, "y": 849}, {"width": 218, "height": 1125, "x": 84, "y": 991}, {"width": 218, "height": 1436, "x": 84, "y": 1302}, {"width": 706, "height": 1440, "x": 592, "y": 0}, {"width": 550, "height": 1280, "x": 442, "y": 362}, {"width": 563, "height": 1429, "x": 429, "y": 1295}, {"width": 542, "height": 111, "x": 449, "y": 21}, {"width": 559, "height": 244, "x": 433, "y": 118}, {"width": 542, "height": 337, "x": 449, "y": 251}]}]}