{"layouts": [{"canvaswidth": 2560, "canvasheight": 1440, "elements": [{"width": 2392, "height": 1440, "x": 0, "y": 0}, {"width": 2374, "height": 775, "x": 2303, "y": 664}, {"width": 770, "height": 982, "x": 245, "y": 457}, {"width": 2259, "height": 1352, "x": 2119, "y": 88}, {"width": 1902, "height": 1352, "x": 1762, "y": 88}, {"width": 2077, "height": 1352, "x": 1937, "y": 88}, {"width": 57, "height": 525, "x": 0, "y": 221}, {"width": 57, "height": 1218, "x": 0, "y": 595}, {"width": 198, "height": 605, "x": 127, "y": 331}, {"width": 197, "height": 1109, "x": 126, "y": 675}, {"width": 338, "height": 558, "x": 267, "y": 206}, {"width": 338, "height": 1233, "x": 267, "y": 628}, {"width": 479, "height": 776, "x": 408, "y": 350}, {"width": 479, "height": 1090, "x": 408, "y": 846}, {"width": 620, "height": 788, "x": 549, "y": 156}, {"width": 620, "height": 1284, "x": 549, "y": 858}, {"width": 761, "height": 521, "x": 690, "y": 334}, {"width": 761, "height": 1106, "x": 690, "y": 591}, {"width": 902, "height": 749, "x": 831, "y": 143}, {"width": 902, "height": 1297, "x": 831, "y": 819}, {"width": 1043, "height": 599, "x": 972, "y": 263}, {"width": 1043, "height": 1176, "x": 972, "y": 669}, {"width": 1184, "height": 758, "x": 1113, "y": 307}, {"width": 1184, "height": 1133, "x": 1113, "y": 828}, {"width": 1325, "height": 700, "x": 1254, "y": 427}, {"width": 1325, "height": 1012, "x": 1254, "y": 770}, {"width": 1466, "height": 1080, "x": 1395, "y": 359}, {"width": 1607, "height": 711, "x": 1536, "y": 201}, {"width": 1607, "height": 1239, "x": 1536, "y": 781}, {"width": 1748, "height": 613, "x": 1677, "y": 255}, {"width": 1748, "height": 1184, "x": 1677, "y": 683}, {"width": 1889, "height": 790, "x": 1818, "y": 275}, {"width": 1889, "height": 1164, "x": 1818, "y": 860}, {"width": 2030, "height": 738, "x": 1959, "y": 296}, {"width": 2030, "height": 1143, "x": 1959, "y": 808}, {"width": 2171, "height": 613, "x": 2100, "y": 269}, {"width": 2171, "height": 1171, "x": 2100, "y": 683}, {"width": 2312, "height": 590, "x": 2241, "y": 283}, {"width": 2312, "height": 1157, "x": 2241, "y": 660}, {"width": 2392, "height": 1080, "x": 2382, "y": 359}]}]}