{"layouts": [{"canvaswidth": 2392, "canvasheight": 1440, "elements": [{"width": 252, "height": 1440, "x": 84, "y": 0}, {"width": 196, "height": 56, "x": 140, "y": 0}, {"width": 224, "height": 155, "x": 112, "y": 43}, {"width": 182, "height": 347, "x": 97, "y": 169}, {"width": 238, "height": 332, "x": 172, "y": 169}, {"width": 2392, "height": 1280, "x": 2217, "y": 160}, {"width": 2392, "height": 1280, "x": 2217, "y": 160}, {"width": 2392, "height": 1280, "x": 2217, "y": 160}, {"width": 425, "height": 676, "x": 252, "y": 116}, {"width": 425, "height": 1352, "x": 252, "y": 792}, {"width": 1006, "height": 676, "x": 481, "y": 116}, {"width": 1006, "height": 1352, "x": 481, "y": 792}, {"width": 1587, "height": 676, "x": 1062, "y": 116}, {"width": 1587, "height": 1352, "x": 1062, "y": 792}, {"width": 2168, "height": 676, "x": 1643, "y": 116}, {"width": 2168, "height": 1352, "x": 1643, "y": 792}]}]}