{"layouts": [{"canvaswidth": 2560, "canvasheight": 1440, "elements": [{"width": 280, "height": 1440, "x": 84, "y": 0}, {"width": 228, "height": 1188, "x": 135, "y": 210}, {"width": 280, "height": 196, "x": 84, "y": 0}, {"width": 1110, "height": 1440, "x": 998, "y": 0}, {"width": 1110, "height": 480, "x": 998, "y": 0}, {"width": 1110, "height": 960, "x": 998, "y": 480}, {"width": 1110, "height": 1440, "x": 998, "y": 960}, {"width": 549, "height": 1147, "x": 409, "y": 1007}, {"width": 873, "height": 415, "x": 733, "y": 275}, {"width": 928, "height": 1384, "x": 678, "y": 440}, {"width": 521, "height": 928, "x": 435, "y": 111}, {"width": 1468, "height": 702, "x": 1128, "y": 21}, {"width": 1468, "height": 702, "x": 1128, "y": 21}, {"width": 1198, "height": 702, "x": 1128, "y": 632}, {"width": 1468, "height": 1418, "x": 1128, "y": 737}, {"width": 1468, "height": 1418, "x": 1128, "y": 737}, {"width": 1843, "height": 702, "x": 1503, "y": 21}, {"width": 1843, "height": 702, "x": 1503, "y": 21}, {"width": 1843, "height": 1418, "x": 1503, "y": 737}, {"width": 1843, "height": 1418, "x": 1503, "y": 737}, {"width": 2218, "height": 702, "x": 1878, "y": 21}, {"width": 2218, "height": 702, "x": 1878, "y": 21}, {"width": 2218, "height": 1418, "x": 1878, "y": 737}, {"width": 2218, "height": 1418, "x": 1878, "y": 737}, {"width": 2392, "height": 702, "x": 2253, "y": 21}, {"width": 2392, "height": 702, "x": 2253, "y": 21}, {"width": 2392, "height": 1418, "x": 2253, "y": 737}, {"width": 2392, "height": 1418, "x": 2253, "y": 737}]}]}