{"layouts": [{"canvaswidth": 2392, "canvasheight": 1440, "elements": [{"width": 218, "height": 880, "x": 125, "y": 560}, {"width": 223, "height": 1405, "x": 120, "y": 1300}, {"width": 224, "height": 140, "x": 119, "y": 35}, {"width": 434, "height": 1280, "x": 259, "y": 160}, {"width": 434, "height": 1280, "x": 259, "y": 160}, {"width": 434, "height": 1280, "x": 259, "y": 160}, {"width": 630, "height": 720, "x": 462, "y": 0}, {"width": 630, "height": 1440, "x": 462, "y": 720}, {"width": 874, "height": 1440, "x": 630, "y": 0}, {"width": 789, "height": 1405, "x": 713, "y": 35}, {"width": 1156, "height": 1440, "x": 874, "y": 0}, {"width": 1119, "height": 245, "x": 909, "y": 35}, {"width": 1085, "height": 1142, "x": 943, "y": 315}, {"width": 1052, "height": 1370, "x": 976, "y": 1177}]}]}