{"layouts": [{"canvaswidth": 2560, "canvasheight": 1440, "elements": [{"width": 280, "height": 1440, "x": 84, "y": 0}, {"width": 228, "height": 655, "x": 135, "y": 210}, {"width": 280, "height": 196, "x": 84, "y": 0}, {"width": 396, "height": 1440, "x": 333, "y": 0}, {"width": 554, "height": 1387, "x": 414, "y": 53}, {"width": 688, "height": 1440, "x": 625, "y": 0}, {"width": 807, "height": 1440, "x": 741, "y": 0}, {"width": 923, "height": 1440, "x": 860, "y": 0}, {"width": 1042, "height": 1440, "x": 976, "y": 0}, {"width": 1361, "height": 693, "x": 1095, "y": 53}, {"width": 1361, "height": 1387, "x": 1095, "y": 746}]}]}