{"layouts": [{"canvaswidth": 2392, "canvasheight": 1440, "elements": [{"width": 168, "height": 168, "x": 0, "y": 0}, {"width": 2198, "height": 1440, "x": 172, "y": 1387}, {"width": 110, "height": 1327, "x": 53, "y": 1303}, {"width": 110, "height": 1363, "x": 53, "y": 1327}, {"width": 110, "height": 1387, "x": 53, "y": 1363}, {"width": 296, "height": 1440, "x": 225, "y": 0}, {"width": 2322, "height": 1440, "x": 2198, "y": 0}, {"width": 2198, "height": 1405, "x": 402, "y": 35}, {"width": 771, "height": 546, "x": 700, "y": 191}, {"width": 771, "height": 1183, "x": 700, "y": 958}, {"width": 1753, "height": 684, "x": 1122, "y": 53}, {"width": 1753, "height": 684, "x": 1613, "y": 53}, {"width": 1753, "height": 1386, "x": 1122, "y": 755}, {"width": 1753, "height": 1386, "x": 1613, "y": 755}, {"width": 2198, "height": 684, "x": 1824, "y": 53}, {"width": 2198, "height": 1386, "x": 1824, "y": 755}]}]}