{"layouts": [{"canvaswidth": 2560, "canvasheight": 1440, "elements": [{"width": 2357, "height": 1370, "x": 2189, "y": 70}, {"width": 138, "height": 908, "x": 35, "y": 531}, {"width": 407, "height": 1349, "x": 138, "y": 91}, {"width": 372, "height": 1314, "x": 173, "y": 126}, {"width": 676, "height": 1349, "x": 407, "y": 91}, {"width": 641, "height": 1314, "x": 442, "y": 126}, {"width": 945, "height": 1349, "x": 676, "y": 91}, {"width": 910, "height": 1314, "x": 711, "y": 126}, {"width": 1214, "height": 1349, "x": 945, "y": 91}, {"width": 1179, "height": 1314, "x": 980, "y": 126}, {"width": 1483, "height": 1349, "x": 1214, "y": 91}, {"width": 1448, "height": 1314, "x": 1249, "y": 126}, {"width": 1752, "height": 1349, "x": 1483, "y": 91}, {"width": 1717, "height": 1314, "x": 1518, "y": 126}, {"width": 2021, "height": 1349, "x": 1752, "y": 91}, {"width": 1986, "height": 1314, "x": 1787, "y": 126}, {"width": 2154, "height": 1349, "x": 2021, "y": 91}]}]}