{"layouts": [{"canvaswidth": 2392, "canvasheight": 1440, "elements": [{"width": 2084, "height": 807, "x": 2049, "y": 632}, {"width": 2084, "height": 807, "x": 2049, "y": 632}, {"width": 1272, "height": 1244, "x": 224, "y": 196}, {"width": 642, "height": 1120, "x": 390, "y": 322}, {"width": 389, "height": 1005, "x": 224, "y": 833}, {"width": 761, "height": 905, "x": 399, "y": 473}, {"width": 1153, "height": 773, "x": 868, "y": 509}, {"width": 1142, "height": 674, "x": 858, "y": 418}, {"width": 1314, "height": 1246, "x": 742, "y": 938}, {"width": 784, "height": 847, "x": 718, "y": 525}, {"width": 1449, "height": 1180, "x": 1377, "y": 259}, {"width": 1664, "height": 1214, "x": 1467, "y": 225}]}]}