{"layouts": [{"canvaswidth": 2560, "canvasheight": 1440, "elements": [{"width": 1478, "height": 1440, "x": 1457, "y": 0}, {"width": 280, "height": 180, "x": 84, "y": 0}, {"width": 280, "height": 1440, "x": 84, "y": 1296}, {"width": 2346, "height": 271, "x": 2283, "y": 208}, {"width": 2347, "height": 755, "x": 2283, "y": 685}, {"width": 2350, "height": 1236, "x": 2280, "y": 1166}, {"width": 1955, "height": 1440, "x": 0, "y": 0}, {"width": 1769, "height": 1387, "x": 1712, "y": 53}, {"width": 1831, "height": 1387, "x": 1774, "y": 53}, {"width": 1892, "height": 1387, "x": 1835, "y": 53}, {"width": 1954, "height": 1387, "x": 1897, "y": 53}, {"width": 2115, "height": 1387, "x": 2058, "y": 53}, {"width": 2392, "height": 1387, "x": 2150, "y": 53}, {"width": 1687, "height": 399, "x": 1572, "y": 49}, {"width": 1687, "height": 507, "x": 1572, "y": 399}]}]}