{"layouts": [{"canvaswidth": 2560, "canvasheight": 1440, "elements": [{"width": 280, "height": 1440, "x": 84, "y": 0}, {"width": 228, "height": 3, "x": 135, "y": 0}, {"width": 267, "height": 175, "x": 95, "y": 3}, {"width": 278, "height": 242, "x": 85, "y": 175}, {"width": 278, "height": 564, "x": 85, "y": 260}, {"width": 267, "height": 1440, "x": 95, "y": 1268}, {"width": 2392, "height": 1440, "x": 280, "y": 0}, {"width": 2392, "height": 1440, "x": 280, "y": 0}, {"width": 1992, "height": 135, "x": 1943, "y": 53}, {"width": 1990, "height": 1266, "x": 1943, "y": 139}, {"width": 1992, "height": 1352, "x": 1943, "y": 1270}, {"width": 2164, "height": 189, "x": 2010, "y": 35}, {"width": 382, "height": 1422, "x": 316, "y": 18}, {"width": 439, "height": 1422, "x": 382, "y": 18}, {"width": 496, "height": 1422, "x": 439, "y": 18}, {"width": 1900, "height": 1440, "x": 521, "y": 0}, {"width": 2161, "height": 1385, "x": 2012, "y": 1271}, {"width": 2164, "height": 797, "x": 2010, "y": 643}, {"width": 2392, "height": 1440, "x": 2182, "y": 0}, {"width": 2364, "height": 797, "x": 2210, "y": 643}, {"width": 2164, "height": 493, "x": 2010, "y": 339}, {"width": 2164, "height": 1101, "x": 2010, "y": 947}, {"width": 2364, "height": 493, "x": 2210, "y": 339}, {"width": 2364, "height": 1101, "x": 2210, "y": 947}]}]}