{"layouts": [{"canvaswidth": 2392, "canvasheight": 1440, "elements": [{"width": 294, "height": 1440, "x": 259, "y": 0}, {"width": 2392, "height": 1440, "x": 2357, "y": 0}, {"width": 1142, "height": 1405, "x": 1076, "y": 35}, {"width": 1280, "height": 1405, "x": 1142, "y": 35}, {"width": 1423, "height": 279, "x": 1357, "y": 35}, {"width": 1455, "height": 538, "x": 1315, "y": 314}, {"width": 242, "height": 477, "x": 102, "y": 35}, {"width": 242, "height": 945, "x": 102, "y": 495}, {"width": 242, "height": 1405, "x": 102, "y": 963}, {"width": 802, "height": 578, "x": 277, "y": 53}, {"width": 343, "height": 1405, "x": 277, "y": 596}, {"width": 481, "height": 1405, "x": 343, "y": 596}, {"width": 582, "height": 1405, "x": 516, "y": 596}, {"width": 718, "height": 1405, "x": 582, "y": 596}, {"width": 903, "height": 360, "x": 837, "y": 35}, {"width": 1041, "height": 360, "x": 903, "y": 35}, {"width": 903, "height": 882, "x": 837, "y": 395}, {"width": 1041, "height": 882, "x": 903, "y": 395}, {"width": 903, "height": 1405, "x": 837, "y": 917}, {"width": 1041, "height": 1405, "x": 903, "y": 917}]}]}