{"layouts": [{"canvaswidth": 2560, "canvasheight": 1440, "elements": [{"width": 2350, "height": 1384, "x": 2210, "y": 224}, {"width": 280, "height": 1440, "x": 84, "y": 0}, {"width": 280, "height": 196, "x": 84, "y": 0}, {"width": 266, "height": 1440, "x": 98, "y": 1300}, {"width": 2322, "height": 168, "x": 2238, "y": 84}, {"width": 894, "height": 1440, "x": 84, "y": 0}, {"width": 373, "height": 1440, "x": 84, "y": 0}, {"width": 1045, "height": 1440, "x": 373, "y": 0}, {"width": 1045, "height": 728, "x": 373, "y": 56}, {"width": 1129, "height": 1440, "x": 1045, "y": 0}, {"width": 1213, "height": 1440, "x": 1129, "y": 0}, {"width": 1220, "height": 1440, "x": 1213, "y": 0}, {"width": 1304, "height": 1440, "x": 1220, "y": 0}, {"width": 1291, "height": 199, "x": 1233, "y": 56}, {"width": 1291, "height": 238, "x": 1233, "y": 227}, {"width": 1291, "height": 388, "x": 1233, "y": 266}, {"width": 1291, "height": 427, "x": 1233, "y": 416}, {"width": 1304, "height": 670, "x": 1220, "y": 455}, {"width": 1332, "height": 1440, "x": 1304, "y": 0}, {"width": 1416, "height": 1440, "x": 1332, "y": 0}, {"width": 1416, "height": 140, "x": 1332, "y": 56}, {"width": 1416, "height": 280, "x": 1332, "y": 196}, {"width": 1416, "height": 560, "x": 1332, "y": 476}, {"width": 1416, "height": 420, "x": 1332, "y": 336}, {"width": 1462, "height": 1440, "x": 1416, "y": 0}, {"width": 1727, "height": 1440, "x": 1462, "y": 0}, {"width": 1811, "height": 1440, "x": 1727, "y": 0}, {"width": 2119, "height": 1440, "x": 1811, "y": 0}, {"width": 2091, "height": 504, "x": 1839, "y": 56}, {"width": 1887, "height": 1300, "x": 1829, "y": 532}, {"width": 1946, "height": 1300, "x": 1887, "y": 532}, {"width": 2077, "height": 490, "x": 2021, "y": 395}, {"width": 1923, "height": 1412, "x": 1839, "y": 1328}, {"width": 1923, "height": 504, "x": 1839, "y": 420}, {"width": 2168, "height": 1440, "x": 2119, "y": 0}, {"width": 2168, "height": 504, "x": 2147, "y": 56}, {"width": 2168, "height": 1300, "x": 2137, "y": 532}, {"width": 2168, "height": 1412, "x": 2147, "y": 1328}, {"width": 2168, "height": 504, "x": 2147, "y": 420}, {"width": 989, "height": 1384, "x": 793, "y": 1188}]}]}