{"layouts": [{"canvaswidth": 2560, "canvasheight": 1440, "elements": [{"width": 280, "height": 1440, "x": 84, "y": 0}, {"width": 228, "height": 906, "x": 135, "y": 210}, {"width": 280, "height": 196, "x": 84, "y": 0}, {"width": 266, "height": 1300, "x": 98, "y": 1132}, {"width": 266, "height": 1440, "x": 98, "y": 1300}, {"width": 2392, "height": 1120, "x": 280, "y": 0}, {"width": 477, "height": 1120, "x": 309, "y": 0}, {"width": 645, "height": 1120, "x": 477, "y": 0}, {"width": 813, "height": 1120, "x": 645, "y": 0}, {"width": 981, "height": 1120, "x": 813, "y": 0}, {"width": 1181, "height": 1120, "x": 1013, "y": 0}, {"width": 1349, "height": 1120, "x": 1181, "y": 0}, {"width": 1517, "height": 1120, "x": 1349, "y": 0}, {"width": 2392, "height": 1440, "x": 2217, "y": 0}, {"width": 448, "height": 1440, "x": 280, "y": 0}, {"width": 448, "height": 720, "x": 280, "y": 0}, {"width": 448, "height": 1440, "x": 280, "y": 720}]}]}