{"layouts": [{"canvaswidth": 2560, "canvasheight": 1440, "elements": [{"width": 280, "height": 1440, "x": 84, "y": 0}, {"width": 228, "height": 469, "x": 135, "y": 210}, {"width": 280, "height": 196, "x": 84, "y": 0}, {"width": 386, "height": 1440, "x": 280, "y": 0}, {"width": 382, "height": 1440, "x": 280, "y": 0}, {"width": 573, "height": 1440, "x": 385, "y": 0}, {"width": 517, "height": 411, "x": 441, "y": 56}, {"width": 760, "height": 1440, "x": 572, "y": 0}, {"width": 704, "height": 169, "x": 628, "y": 56}, {"width": 947, "height": 1440, "x": 759, "y": 0}, {"width": 891, "height": 240, "x": 815, "y": 56}, {"width": 1134, "height": 1440, "x": 946, "y": 0}, {"width": 1078, "height": 396, "x": 1002, "y": 56}, {"width": 1321, "height": 1440, "x": 1133, "y": 0}, {"width": 1265, "height": 595, "x": 1189, "y": 56}, {"width": 1508, "height": 1440, "x": 1320, "y": 0}, {"width": 1452, "height": 202, "x": 1376, "y": 56}, {"width": 1613, "height": 1440, "x": 1507, "y": 0}, {"width": 1609, "height": 1440, "x": 1507, "y": 0}, {"width": 1800, "height": 1440, "x": 1612, "y": 0}, {"width": 1744, "height": 453, "x": 1668, "y": 56}, {"width": 1987, "height": 1440, "x": 1799, "y": 0}, {"width": 1931, "height": 260, "x": 1855, "y": 56}, {"width": 2092, "height": 1440, "x": 1986, "y": 0}, {"width": 2088, "height": 1440, "x": 1986, "y": 0}, {"width": 2345, "height": 1440, "x": 2091, "y": 0}, {"width": 2302, "height": 211, "x": 2134, "y": 43}, {"width": 2223, "height": 541, "x": 2147, "y": 253}, {"width": 2289, "height": 1050, "x": 2223, "y": 253}, {"width": 2392, "height": 1440, "x": 2344, "y": 0}, {"width": 2392, "height": 211, "x": 2387, "y": 43}]}]}