{"layouts": [{"canvaswidth": 2560, "canvasheight": 1440, "elements": [{"width": 252, "height": 1440, "x": 84, "y": 0}, {"width": 216, "height": 1440, "x": 119, "y": 0}, {"width": 206, "height": 1398, "x": 129, "y": 1321}, {"width": 2364, "height": 1384, "x": 2196, "y": 56}, {"width": 434, "height": 1384, "x": 294, "y": 56}, {"width": 517, "height": 310, "x": 462, "y": 56}, {"width": 824, "height": 366, "x": 769, "y": 56}, {"width": 657, "height": 362, "x": 587, "y": 98}, {"width": 643, "height": 1342, "x": 601, "y": 1315}, {"width": 964, "height": 334, "x": 894, "y": 98}, {"width": 950, "height": 1342, "x": 908, "y": 1315}, {"width": 1140, "height": 1412, "x": 1062, "y": 28}, {"width": 1340, "height": 829, "x": 1168, "y": 553}, {"width": 1340, "height": 1105, "x": 1168, "y": 898}, {"width": 1340, "height": 1381, "x": 1168, "y": 1174}, {"width": 1326, "height": 538, "x": 1182, "y": 526}, {"width": 1326, "height": 882, "x": 1182, "y": 845}, {"width": 1326, "height": 1150, "x": 1182, "y": 1128}, {"width": 1284, "height": 193, "x": 1221, "y": 70}]}]}