{"layouts": [{"canvaswidth": 2392, "canvasheight": 1440, "elements": [{"width": 2392, "height": 1440, "x": 84, "y": 0}, {"width": 223, "height": 1094, "x": 132, "y": 345}, {"width": 212, "height": 108, "x": 144, "y": 40}, {"width": 234, "height": 1380, "x": 122, "y": 1188}, {"width": 803, "height": 1328, "x": 587, "y": 112}, {"width": 543, "height": 415, "x": 451, "y": 323}, {"width": 545, "height": 1085, "x": 448, "y": 463}, {"width": 543, "height": 1257, "x": 451, "y": 1165}, {"width": 1019, "height": 1328, "x": 859, "y": 208}, {"width": 1874, "height": 1128, "x": 1783, "y": 968}, {"width": 1869, "height": 1208, "x": 1789, "y": 1128}, {"width": 2203, "height": 1328, "x": 2043, "y": 208}, {"width": 1191, "height": 1272, "x": 1081, "y": 168}, {"width": 1363, "height": 1272, "x": 1253, "y": 168}, {"width": 1535, "height": 1272, "x": 1425, "y": 168}, {"width": 1707, "height": 1272, "x": 1597, "y": 168}, {"width": 2375, "height": 1272, "x": 2265, "y": 168}]}]}