{"layouts": [{"canvaswidth": 2392, "canvasheight": 1440, "elements": [{"width": 164, "height": 1440, "x": 84, "y": 0}, {"width": 550, "height": 360, "x": 340, "y": 0}, {"width": 550, "height": 720, "x": 340, "y": 360}, {"width": 550, "height": 1080, "x": 340, "y": 720}, {"width": 2392, "height": 1371, "x": 2316, "y": 1037}, {"width": 2382, "height": 1440, "x": 2326, "y": 1371}, {"width": 316, "height": 1206, "x": 187, "y": 1077}, {"width": 302, "height": 612, "x": 201, "y": 18}, {"width": 428, "height": 1305, "x": 358, "y": 1214}, {"width": 532, "height": 1379, "x": 428, "y": 1141}, {"width": 655, "height": 476, "x": 550, "y": 0}, {"width": 655, "height": 956, "x": 550, "y": 480}, {"width": 655, "height": 1436, "x": 550, "y": 960}, {"width": 871, "height": 1440, "x": 659, "y": 0}, {"width": 752, "height": 1440, "x": 659, "y": 0}, {"width": 871, "height": 504, "x": 752, "y": 0}, {"width": 871, "height": 1296, "x": 752, "y": 792}, {"width": 871, "height": 1440, "x": 752, "y": 1296}, {"width": 841, "height": 792, "x": 782, "y": 521}, {"width": 990, "height": 1440, "x": 871, "y": 0}, {"width": 990, "height": 504, "x": 871, "y": 0}, {"width": 990, "height": 1296, "x": 871, "y": 792}, {"width": 990, "height": 1440, "x": 871, "y": 1296}, {"width": 960, "height": 792, "x": 901, "y": 521}, {"width": 1202, "height": 1440, "x": 990, "y": 0}, {"width": 1083, "height": 1440, "x": 990, "y": 0}, {"width": 1202, "height": 504, "x": 1083, "y": 0}, {"width": 1202, "height": 1296, "x": 1083, "y": 792}, {"width": 1202, "height": 1440, "x": 1083, "y": 1296}, {"width": 1172, "height": 792, "x": 1113, "y": 521}, {"width": 1321, "height": 1440, "x": 1202, "y": 0}, {"width": 1321, "height": 504, "x": 1202, "y": 0}, {"width": 1321, "height": 1296, "x": 1202, "y": 792}, {"width": 1321, "height": 1440, "x": 1202, "y": 1296}, {"width": 1291, "height": 792, "x": 1232, "y": 521}, {"width": 1533, "height": 1440, "x": 1321, "y": 0}, {"width": 1414, "height": 1440, "x": 1321, "y": 0}, {"width": 1533, "height": 504, "x": 1414, "y": 0}, {"width": 1533, "height": 1296, "x": 1414, "y": 792}, {"width": 1533, "height": 1440, "x": 1414, "y": 1296}, {"width": 1503, "height": 792, "x": 1444, "y": 521}, {"width": 1652, "height": 1440, "x": 1533, "y": 0}, {"width": 1652, "height": 504, "x": 1533, "y": 0}, {"width": 1652, "height": 1296, "x": 1533, "y": 792}, {"width": 1652, "height": 1440, "x": 1533, "y": 1296}, {"width": 1622, "height": 792, "x": 1563, "y": 521}, {"width": 1864, "height": 1440, "x": 1652, "y": 0}, {"width": 1745, "height": 1440, "x": 1652, "y": 0}, {"width": 1864, "height": 504, "x": 1745, "y": 0}, {"width": 1864, "height": 1296, "x": 1745, "y": 792}, {"width": 1864, "height": 1440, "x": 1745, "y": 1296}, {"width": 1834, "height": 792, "x": 1775, "y": 521}, {"width": 1983, "height": 1440, "x": 1864, "y": 0}, {"width": 1983, "height": 504, "x": 1864, "y": 0}, {"width": 1983, "height": 1296, "x": 1864, "y": 792}, {"width": 1983, "height": 1440, "x": 1864, "y": 1296}, {"width": 1953, "height": 792, "x": 1894, "y": 521}, {"width": 2195, "height": 1440, "x": 1983, "y": 0}, {"width": 2076, "height": 1440, "x": 1983, "y": 0}, {"width": 2195, "height": 504, "x": 2076, "y": 0}, {"width": 2195, "height": 1296, "x": 2076, "y": 792}, {"width": 2195, "height": 1440, "x": 2076, "y": 1296}, {"width": 2165, "height": 792, "x": 2106, "y": 521}, {"width": 2314, "height": 1440, "x": 2195, "y": 0}, {"width": 2314, "height": 504, "x": 2195, "y": 0}, {"width": 2314, "height": 1296, "x": 2195, "y": 792}, {"width": 2314, "height": 1440, "x": 2195, "y": 1296}, {"width": 2284, "height": 792, "x": 2225, "y": 521}, {"width": 2316, "height": 1440, "x": 2314, "y": 0}, {"width": 2316, "height": 1440, "x": 2314, "y": 0}, {"width": 322, "height": 1077, "x": 182, "y": 937}, {"width": 302, "height": 1331, "x": 167, "y": 1252}]}]}