{"layouts": [{"canvaswidth": 2560, "canvasheight": 1440, "elements": [{"width": 280, "height": 1440, "x": 84, "y": 0}, {"width": 228, "height": 620, "x": 135, "y": 210}, {"width": 280, "height": 196, "x": 84, "y": 0}, {"width": 910, "height": 1440, "x": 280, "y": 0}, {"width": 910, "height": 1440, "x": 280, "y": 0}, {"width": 895, "height": 1428, "x": 295, "y": 12}, {"width": 895, "height": 1428, "x": 727, "y": 12}, {"width": 1540, "height": 1440, "x": 910, "y": 0}, {"width": 1540, "height": 1440, "x": 910, "y": 0}, {"width": 1525, "height": 1428, "x": 925, "y": 12}, {"width": 1525, "height": 1428, "x": 1357, "y": 12}, {"width": 2170, "height": 1440, "x": 1540, "y": 0}, {"width": 2170, "height": 1440, "x": 1540, "y": 0}, {"width": 2155, "height": 1428, "x": 1555, "y": 12}, {"width": 2155, "height": 1428, "x": 1987, "y": 12}, {"width": 2392, "height": 1440, "x": 2170, "y": 0}, {"width": 2392, "height": 1440, "x": 2170, "y": 0}, {"width": 2392, "height": 1428, "x": 2185, "y": 12}]}]}