{"layouts": [{"canvasheight": 1440, "canvaswidth": 2560, "elements": [{"y": 259, "x": 105, "height": 431, "width": 231}, {"y": 7, "x": 84, "height": 203, "width": 252}, {"y": 1261, "x": 91, "height": 1415, "width": 245}, {"y": 0, "x": 84, "height": 1440, "width": 280}, {"y": 0, "x": 294, "height": 1440, "width": 434}, {"y": 70, "x": 434, "height": 1370, "width": 616}, {"y": 70, "x": 434, "height": 359, "width": 616}, {"y": 359, "x": 434, "height": 1370, "width": 616}, {"y": 70, "x": 616, "height": 1370, "width": 798}, {"y": 70, "x": 616, "height": 426, "width": 798}, {"y": 426, "x": 616, "height": 1370, "width": 798}, {"y": 70, "x": 798, "height": 1370, "width": 980}, {"y": 70, "x": 798, "height": 321, "width": 980}, {"y": 70, "x": 980, "height": 1370, "width": 1166}, {"y": 70, "x": 980, "height": 1204, "width": 1162}, {"y": 1204, "x": 1023, "height": 1370, "width": 1118}, {"y": 70, "x": 1166, "height": 1370, "width": 1348}, {"y": 70, "x": 1166, "height": 415, "width": 1348}, {"y": 415, "x": 1166, "height": 1370, "width": 1348}]}]}