{"layouts": [{"canvasheight": 1440, "canvaswidth": 2560, "elements": [{"y": 0, "x": 84, "height": 196, "width": 280}, {"y": 252, "x": 139, "height": 1440, "width": 224}, {"y": 0, "x": 84, "height": 1440, "width": 280}, {"y": 160, "x": 2217, "height": 1280, "width": 2392}, {"y": 160, "x": 2217, "height": 1280, "width": 2392}, {"y": 160, "x": 2217, "height": 1280, "width": 2392}, {"y": 163, "x": 310, "height": 253, "width": 436}, {"y": 267, "x": 310, "height": 282, "width": 436}, {"y": 296, "x": 310, "height": 1284, "width": 436}, {"y": 62, "x": 346, "height": 135, "width": 399}, {"y": 1319, "x": 345, "height": 1375, "width": 401}, {"y": 0, "x": 280, "height": 1440, "width": 447}, {"y": 170, "x": 458, "height": 611, "width": 598}, {"y": 828, "x": 458, "height": 1270, "width": 598}, {"y": 632, "x": 477, "height": 719, "width": 579}, {"y": 720, "x": 477, "height": 807, "width": 579}, {"y": 72, "x": 465, "height": 128, "width": 521}, {"y": 72, "x": 541, "height": 128, "width": 584}, {"y": 0, "x": 447, "height": 1440, "width": 628}, {"y": 163, "x": 658, "height": 344, "width": 784}, {"y": 358, "x": 658, "height": 373, "width": 784}, {"y": 387, "x": 658, "height": 1284, "width": 784}, {"y": 62, "x": 694, "height": 135, "width": 747}, {"y": 1319, "x": 693, "height": 1375, "width": 749}, {"y": 0, "x": 628, "height": 1440, "width": 795}, {"y": 170, "x": 806, "height": 611, "width": 946}, {"y": 828, "x": 806, "height": 1270, "width": 946}, {"y": 632, "x": 825, "height": 719, "width": 927}, {"y": 720, "x": 825, "height": 807, "width": 927}, {"y": 72, "x": 813, "height": 128, "width": 869}, {"y": 72, "x": 889, "height": 128, "width": 932}, {"y": 0, "x": 795, "height": 1440, "width": 976}, {"y": 163, "x": 1006, "height": 344, "width": 1132}, {"y": 358, "x": 1006, "height": 373, "width": 1132}, {"y": 387, "x": 1006, "height": 1284, "width": 1132}, {"y": 62, "x": 1042, "height": 135, "width": 1095}, {"y": 1319, "x": 1041, "height": 1375, "width": 1097}, {"y": 0, "x": 976, "height": 1440, "width": 1143}, {"y": 170, "x": 1154, "height": 611, "width": 1294}, {"y": 828, "x": 1154, "height": 1270, "width": 1294}, {"y": 632, "x": 1173, "height": 719, "width": 1275}, {"y": 720, "x": 1173, "height": 807, "width": 1275}, {"y": 72, "x": 1161, "height": 128, "width": 1217}, {"y": 72, "x": 1237, "height": 128, "width": 1280}, {"y": 0, "x": 1143, "height": 1440, "width": 1324}, {"y": 163, "x": 1354, "height": 477, "width": 1480}, {"y": 491, "x": 1354, "height": 506, "width": 1480}, {"y": 520, "x": 1354, "height": 1284, "width": 1480}, {"y": 62, "x": 1390, "height": 135, "width": 1443}, {"y": 1319, "x": 1389, "height": 1375, "width": 1445}, {"y": 0, "x": 1324, "height": 1440, "width": 1491}, {"y": 170, "x": 1502, "height": 611, "width": 1642}, {"y": 828, "x": 1502, "height": 1270, "width": 1642}, {"y": 632, "x": 1521, "height": 719, "width": 1623}, {"y": 720, "x": 1521, "height": 807, "width": 1623}, {"y": 72, "x": 1509, "height": 128, "width": 1565}, {"y": 72, "x": 1585, "height": 128, "width": 1628}, {"y": 0, "x": 1491, "height": 1440, "width": 1653}, {"y": 170, "x": 1664, "height": 611, "width": 1804}, {"y": 828, "x": 1664, "height": 1270, "width": 1804}, {"y": 632, "x": 1683, "height": 719, "width": 1785}, {"y": 720, "x": 1683, "height": 807, "width": 1785}, {"y": 72, "x": 1671, "height": 128, "width": 1727}, {"y": 72, "x": 1747, "height": 128, "width": 1790}, {"y": 0, "x": 1653, "height": 1440, "width": 1834}, {"y": 163, "x": 1864, "height": 241, "width": 1990}, {"y": 255, "x": 1864, "height": 270, "width": 1990}, {"y": 284, "x": 1864, "height": 1284, "width": 1990}, {"y": 62, "x": 1900, "height": 135, "width": 1953}, {"y": 1319, "x": 1899, "height": 1375, "width": 1955}, {"y": 0, "x": 1834, "height": 1440, "width": 2001}, {"y": 170, "x": 2012, "height": 611, "width": 2152}, {"y": 828, "x": 2012, "height": 1270, "width": 2152}, {"y": 632, "x": 2031, "height": 719, "width": 2133}, {"y": 720, "x": 2031, "height": 807, "width": 2133}, {"y": 72, "x": 2019, "height": 128, "width": 2075}, {"y": 72, "x": 2095, "height": 128, "width": 2138}, {"y": 0, "x": 2001, "height": 1440, "width": 2163}, {"y": 170, "x": 2174, "height": 611, "width": 2213}, {"y": 828, "x": 2174, "height": 1270, "width": 2213}, {"y": 632, "x": 2193, "height": 719, "width": 2213}, {"y": 720, "x": 2193, "height": 807, "width": 2213}, {"y": 72, "x": 2181, "height": 128, "width": 2213}, {"y": 0, "x": 2163, "height": 1440, "width": 2213}]}]}