{"layouts": [{"canvasheight": 1440, "canvaswidth": 2560, "elements": [{"y": 303, "x": 242, "height": 1136, "width": 492}, {"y": 308, "x": 1116, "height": 1132, "width": 1218}, {"y": 48, "x": 492, "height": 1392, "width": 589}, {"y": 48, "x": 589, "height": 1392, "width": 680}, {"y": 48, "x": 797, "height": 1392, "width": 888}, {"y": 48, "x": 1005, "height": 1392, "width": 1096}, {"y": 329, "x": 1218, "height": 700, "width": 1320}, {"y": 700, "x": 1218, "height": 797, "width": 1320}, {"y": 797, "x": 1218, "height": 1111, "width": 1320}, {"y": 96, "x": 1320, "height": 1343, "width": 1557}, {"y": 296, "x": 1605, "height": 915, "width": 1774}, {"y": 915, "x": 1605, "height": 1143, "width": 1774}]}]}