{"layouts": [{"canvasheight": 1440, "canvaswidth": 2392, "elements": [{"y": 608, "x": 1542, "height": 832, "width": 1710}, {"y": 35, "x": 2189, "height": 704, "width": 2357}, {"y": 718, "x": 2189, "height": 1405, "width": 2357}, {"y": 887, "x": 1111, "height": 1111, "width": 1196}, {"y": 887, "x": 839, "height": 1111, "width": 1469}, {"y": 329, "x": 1111, "height": 553, "width": 1196}, {"y": 329, "x": 839, "height": 553, "width": 1469}, {"y": 574, "x": 1121, "height": 586, "width": 1187}, {"y": 607, "x": 1111, "height": 831, "width": 1196}, {"y": 607, "x": 839, "height": 831, "width": 1469}]}]}