{"layouts": [{"canvasheight": 1440, "canvaswidth": 2560, "elements": [{"y": 196, "x": 139, "height": 381, "width": 224}, {"y": 0, "x": 84, "height": 196, "width": 280}, {"y": 0, "x": 84, "height": 1440, "width": 280}, {"y": 14, "x": 280, "height": 713, "width": 521}, {"y": 21, "x": 280, "height": 706, "width": 374}, {"y": 32, "x": 374, "height": 706, "width": 514}, {"y": 727, "x": 280, "height": 1426, "width": 521}, {"y": 734, "x": 280, "height": 1419, "width": 374}, {"y": 745, "x": 374, "height": 1419, "width": 514}, {"y": 14, "x": 535, "height": 713, "width": 1374}, {"y": 21, "x": 542, "height": 706, "width": 1227}, {"y": 32, "x": 1227, "height": 706, "width": 1367}, {"y": 727, "x": 535, "height": 1426, "width": 1374}, {"y": 734, "x": 542, "height": 1419, "width": 1227}, {"y": 745, "x": 1227, "height": 1419, "width": 1367}, {"y": 14, "x": 1388, "height": 713, "width": 2227}, {"y": 21, "x": 1395, "height": 706, "width": 2080}, {"y": 32, "x": 2080, "height": 706, "width": 2220}, {"y": 727, "x": 1388, "height": 1426, "width": 2227}, {"y": 734, "x": 1395, "height": 1419, "width": 2080}, {"y": 745, "x": 2080, "height": 1419, "width": 2220}, {"y": 14, "x": 2241, "height": 713, "width": 2392}, {"y": 21, "x": 2248, "height": 706, "width": 2392}, {"y": 727, "x": 2241, "height": 1426, "width": 2392}, {"y": 734, "x": 2248, "height": 1419, "width": 2392}]}]}