{"layouts": [{"canvasheight": 1440, "canvaswidth": 2560, "elements": [{"y": 0, "x": 1524, "height": 1440, "width": 1678}, {"y": 25, "x": 2217, "height": 713, "width": 2375}, {"y": 727, "x": 2217, "height": 1415, "width": 2375}, {"y": 28, "x": 105, "height": 168, "width": 245}, {"y": 370, "x": 130, "height": 1070, "width": 220}, {"y": 1279, "x": 101, "height": 1426, "width": 248}, {"y": 0, "x": 84, "height": 1440, "width": 1524}, {"y": 0, "x": 84, "height": 1440, "width": 1524}, {"y": 549, "x": 756, "height": 891, "width": 837}, {"y": 56, "x": 1120, "height": 116, "width": 1180}, {"y": 622, "x": 872, "height": 699, "width": 949}, {"y": 741, "x": 872, "height": 818, "width": 949}, {"y": 198, "x": 1012, "height": 272, "width": 1061}, {"y": 158, "x": 1159, "height": 1046, "width": 1246}, {"y": 4, "x": 1699, "height": 358, "width": 2053}, {"y": 4, "x": 1699, "height": 358, "width": 2053}, {"y": 363, "x": 1699, "height": 717, "width": 2053}, {"y": 363, "x": 1699, "height": 717, "width": 2053}, {"y": 722, "x": 1699, "height": 1076, "width": 2053}, {"y": 722, "x": 1699, "height": 1076, "width": 2053}, {"y": 580, "x": 434, "height": 860, "width": 714}, {"y": 70, "x": 1019, "height": 105, "width": 1054}, {"y": 116, "x": 1013, "height": 156, "width": 1060}, {"y": 986, "x": 1011, "height": 1028, "width": 1053}, {"y": 1039, "x": 1004, "height": 1384, "width": 1061}, {"y": 46, "x": 2134, "height": 379, "width": 2210}, {"y": 1274, "x": 2159, "height": 1300, "width": 2185}, {"y": 1380, "x": 2149, "height": 1405, "width": 2195}, {"y": 46, "x": 2331, "height": 379, "width": 2392}, {"y": 413, "x": 2336, "height": 498, "width": 2392}, {"y": 1274, "x": 2356, "height": 1300, "width": 2382}, {"y": 1380, "x": 2346, "height": 1405, "width": 2392}, {"y": 413, "x": 2139, "height": 766, "width": 2205}]}]}