{"layouts": [{"canvasheight": 1440, "canvaswidth": 2560, "elements": [{"y": 252, "x": 135, "height": 809, "width": 228}, {"y": 0, "x": 84, "height": 196, "width": 280}, {"y": 1048, "x": 98, "height": 1244, "width": 266}, {"y": 1244, "x": 98, "height": 1440, "width": 266}, {"y": 0, "x": 84, "height": 1440, "width": 280}, {"y": 51, "x": 280, "height": 177, "width": 294}, {"y": 86, "x": 313, "height": 1256, "width": 379}, {"y": 1256, "x": 294, "height": 1361, "width": 399}, {"y": 28, "x": 280, "height": 1412, "width": 433}, {"y": 51, "x": 467, "height": 177, "width": 616}, {"y": 195, "x": 499, "height": 1109, "width": 584}, {"y": 86, "x": 635, "height": 1256, "width": 701}, {"y": 1256, "x": 616, "height": 1361, "width": 721}, {"y": 28, "x": 433, "height": 1412, "width": 755}, {"y": 51, "x": 789, "height": 177, "width": 938}, {"y": 195, "x": 821, "height": 1109, "width": 906}, {"y": 86, "x": 957, "height": 1256, "width": 1023}, {"y": 1256, "x": 938, "height": 1361, "width": 1043}, {"y": 28, "x": 755, "height": 1412, "width": 1077}, {"y": 28, "x": 1077, "height": 1412, "width": 1926}, {"y": 301, "x": 1105, "height": 721, "width": 1898}, {"y": 860, "x": 1424, "height": 1000, "width": 1564}, {"y": 868, "x": 1126, "height": 1071, "width": 1192}, {"y": 887, "x": 1203, "height": 1053, "width": 1279}, {"y": 56, "x": 1993, "height": 692, "width": 2161}, {"y": 748, "x": 1993, "height": 1384, "width": 2161}]}]}